hello1234.py
hello1234-0.0.2.dist-info/DESCRIPTION.rst
hello1234-0.0.2.dist-info/METADATA
hello1234-0.0.2.dist-info/RECORD
hello1234-0.0.2.dist-info/WHEEL
hello1234-0.0.2.dist-info/entry_points.txt
hello1234-0.0.2.dist-info/metadata.json
hello1234-0.0.2.dist-info/top_level.txt
