Metadata-Version: 2.0
Name: hello1234
Version: 0.0.2
Summary: A module / utility to greet people.
Home-page: https://github.com/denesnori/helloworld1234
Author: Nora Denes
Author-email: denes.nori@yahoo.com
License: MIT
Platform: UNKNOWN
Classifier: Development Status :: 4 - Beta
Classifier: Environment :: Console
Classifier: Intended Audience :: Developers
Classifier: Intended Audience :: Education
